[
  {
    "part_name": "Brake Pads",
    "part_number": "BP-001",
    "part_description": "High-performance ceramic brake pads for improved stopping power.",
    "price": 45.99,
    "brand_name": "Brembo",
    "part_type": "Braking System"
  },
  {
    "part_name": "Oil Filter",
    "part_number": "OF-023",
    "part_description": "Premium oil filter for enhanced engine protection.",
    "price": 12.5,
    "brand_name": "Fram",
    "part_type": "Engine"
  },
  {
    "part_name": "Spark Plug",
    "part_number": "SP-009",
    "part_description": "Iridium spark plug for better fuel efficiency and durability.",
    "price": 8.99,
    "brand_name": "NGK",
    "part_type": "Ignition System"
  },
  {
    "part_name": "Air Filter",
    "part_number": "AF-045",
    "part_description": "High-flow air filter for increased engine performance.",
    "price": 15.75,
    "brand_name": "K&N",
    "part_type": "Engine"
  },
  {
    "part_name": "Alternator",
    "part_number": "ALT-017",
    "part_description": "150A alternator for reliable electrical power supply.",
    "price": 129.99,
    "brand_name": "Bosch",
    "part_type": "Electrical System"
  },
  {
    "part_name": "Radiator",
    "part_number": "RAD-003",
    "part_description": "Aluminum radiator for efficient engine cooling.",
    "price": 89,
    "brand_name": "Denso",
    "part_type": "Cooling System"
  },
  {
    "part_name": "Fuel Pump",
    "part_number": "FP-012",
    "part_description": "Electric fuel pump with high-pressure output.",
    "price": 65.45,
    "brand_name": "Delphi",
    "part_type": "Fuel System"
  },
  {
    "part_name": "Timing Belt",
    "part_number": "TB-008",
    "part_description": "Durable timing belt for precise engine timing.",
    "price": 29.99,
    "brand_name": "Gates",
    "part_type": "Engine"
  },
  {
    "part_name": "Shock Absorber",
    "part_number": "SA-019",
    "part_description": "Gas-charged shock absorber for smooth ride.",
    "price": 55,
    "brand_name": "Monroe",
    "part_type": "Suspension System"
  },
  {
    "part_name": "Battery",
    "part_number": "BAT-004",
    "part_description": "12V lead-acid battery with 650 CCA.",
    "price": 99.95,
    "brand_name": "Optima",
    "part_type": "Electrical System"
  },
  {
    "part_name": "Exhaust Muffler",
    "part_number": "EM-022",
    "part_description": "Stainless steel muffler for reduced noise.",
    "price": 75.5,
    "brand_name": "MagnaFlow",
    "part_type": "Exhaust System"
  },
  {
    "part_name": "Clutch Kit",
    "part_number": "CK-015",
    "part_description": "Complete clutch kit for manual transmissions.",
    "price": 149.99,
    "brand_name": "Luk",
    "part_type": "Transmission"
  },
  {
    "part_name": "Wheel Bearing",
    "part_number": "WB-007",
    "part_description": "Sealed wheel bearing for reduced friction.",
    "price": 34.25,
    "brand_name": "SKF",
    "part_type": "Suspension System"
  },
  {
    "part_name": "Headlight Assembly",
    "part_number": "HL-011",
    "part_description": "LED headlight assembly for improved visibility.",
    "price": 120,
    "brand_name": "Philips",
    "part_type": "Lighting"
  },
  {
    "part_name": "Thermostat",
    "part_number": "TH-006",
    "part_description": "Engine thermostat for temperature regulation.",
    "price": 19.99,
    "brand_name": "Stant",
    "part_type": "Cooling System"
  },
  {
    "part_name": "Brake Rotor",
    "part_number": "BR-013",
    "part_description": "Vented brake rotor for enhanced heat dissipation.",
    "price": 60.75,
    "brand_name": "ACDelco",
    "part_type": "Braking System"
  },
  {
    "part_name": "Ignition Coil",
    "part_number": "IC-010",
    "part_description": "High-output ignition coil for reliable spark.",
    "price": 39.95,
    "brand_name": "Denso",
    "part_type": "Ignition System"
  },
  {
    "part_name": "Water Pump",
    "part_number": "WP-005",
    "part_description": "High-flow water pump for engine cooling.",
    "price": 45,
    "brand_name": "GMB",
    "part_type": "Cooling System"
  },
  {
    "part_name": "Starter Motor",
    "part_number": "SM-014",
    "part_description": "Heavy-duty starter motor for quick engine start.",
    "price": 110.5,
    "brand_name": "Remy",
    "part_type": "Electrical System"
  },
  {
    "part_name": "Fuel Injector",
    "part_number": "FI-018",
    "part_description": "Precision fuel injector for optimal fuel delivery.",
    "price": 55.99,
    "brand_name": "Bosch",
    "part_type": "Fuel System"
  },
  {
    "part_name": "Control Arm",
    "part_number": "CA-020",
    "part_description": "Steel control arm for suspension stability.",
    "price": 70.25,
    "brand_name": "Moog",
    "part_type": "Suspension System"
  },
  {
    "part_name": "Catalytic Converter",
    "part_number": "CC-016",
    "part_description": "Direct-fit catalytic converter for emissions control.",
    "price": 199.99,
    "brand_name": "Walker",
    "part_type": "Exhaust System"
  },
  {
    "part_name": "Power Steering Pump",
    "part_number": "PSP-021",
    "part_description": "Hydraulic power steering pump for smooth steering.",
    "price": 85,
    "brand_name": "Cardone",
    "part_type": "Steering System"
  },
  {
    "part_name": "Oxygen Sensor",
    "part_number": "OS-024",
    "part_description": "Wideband oxygen sensor for precise air-fuel ratio.",
    "price": 49.95,
    "brand_name": "NGK",
    "part_type": "Exhaust System"
  },
  {
    "part_name": "Transmission Filter",
    "part_number": "TF-025",
    "part_description": "Transmission filter kit with gasket.",
    "price": 22.5,
    "brand_name": "WIX",
    "part_type": "Transmission"
  },
  {
    "part_name": "Tie Rod End",
    "part_number": "TRE-026",
    "part_description": "Adjustable tie rod end for steering alignment.",
    "price": 28.75,
    "brand_name": "Moog",
    "part_type": "Steering System"
  },
  {
    "part_name": "Brake Caliper",
    "part_number": "BC-027",
    "part_description": "Remanufactured brake caliper for consistent braking.",
    "price": 65,
    "brand_name": "Raybestos",
    "part_type": "Braking System"
  },
  {
    "part_name": "Serpentine Belt",
    "part_number": "SB-028",
    "part_description": "Multi-rib serpentine belt for accessory drive.",
    "price": 19.99,
    "brand_name": "Dayco",
    "part_type": "Engine"
  },
  {
    "part_name": "Mass Air Flow Sensor",
    "part_number": "MAF-029",
    "part_description": "MAF sensor for accurate air intake measurement.",
    "price": 79.95,
    "brand_name": "Hitachi",
    "part_type": "Engine"
  },
  {
    "part_name": "Ball Joint",
    "part_number": "BJ-030",
    "part_description": "Greaseable ball joint for suspension durability.",
    "price": 25.5,
    "brand_name": "TRW",
    "part_type": "Suspension System"
  },
  {
    "part_name": "Distributor Cap",
    "part_number": "DC-031",
    "part_description": "Distributor cap for reliable spark distribution.",
    "price": 14.99,
    "brand_name": "Standard",
    "part_type": "Ignition System"
  },
  {
    "part_name": "Fuel Tank Cap",
    "part_number": "FTC-032",
    "part_description": "Locking fuel cap for secure fuel tank sealing.",
    "price": 9.75,
    "brand_name": "Stant",
    "part_type": "Fuel System"
  },
  {
    "part_name": "Radiator Hose",
    "part_number": "RH-033",
    "part_description": "Reinforced radiator hose for coolant flow.",
    "price": 12.25,
    "brand_name": "Gates",
    "part_type": "Cooling System"
  },
  {
    "part_name": "CV Joint",
    "part_number": "CVJ-034",
    "part_description": "Constant velocity joint for smooth power transfer.",
    "price": 45,
    "brand_name": "GKN",
    "part_type": "Drivetrain"
  },
  {
    "part_name": "Tail Light Assembly",
    "part_number": "TL-035",
    "part_description": "LED tail light assembly for enhanced visibility.",
    "price": 95.5,
    "brand_name": "TYC",
    "part_type": "Lighting"
  },
  {
    "part_name": "Cabin Air Filter",
    "part_number": "CAF-036",
    "part_description": "Activated carbon cabin filter for clean air.",
    "price": 17.99,
    "brand_name": "Purolator",
    "part_type": "Interior"
  },
  {
    "part_name": "EGR Valve",
    "part_number": "EGR-037",
    "part_description": "Exhaust gas recirculation valve for emissions control.",
    "price": 65.75,
    "brand_name": "Delphi",
    "part_type": "Exhaust System"
  },
  {
    "part_name": "Throttle Body",
    "part_number": "TB-038",
    "part_description": "Electronic throttle body for precise air control.",
    "price": 110,
    "brand_name": "Bosch",
    "part_type": "Engine"
  },
  {
    "part_name": "Wheel Hub Assembly",
    "part_number": "WHA-039",
    "part_description": "Complete wheel hub with integrated bearing.",
    "price": 85.25,
    "brand_name": "Timken",
    "part_type": "Suspension System"
  },
  {
    "part_name": "PCV Valve",
    "part_number": "PCV-040",
    "part_description": "Positive crankcase ventilation valve for emissions.",
    "price": 7.99,
    "brand_name": "FRAM",
    "part_type": "Engine"
  },
  {
    "part_name": "Brake Master Cylinder",
    "part_number": "BMC-041",
    "part_description": "Master cylinder for hydraulic brake system.",
    "price": 95,
    "brand_name": "Wagner",
    "part_type": "Braking System"
  },
  {
    "part_name": "Fuel Pressure Regulator",
    "part_number": "FPR-042",
    "part_description": "Regulator for consistent fuel pressure.",
    "price": 35.5,
    "brand_name": "ACDelco",
    "part_type": "Fuel System"
  },
  {
    "part_name": "Strut Assembly",
    "part_number": "STA-043",
    "part_description": "Complete strut assembly for suspension support.",
    "price": 115.99,
    "brand_name": "KYB",
    "part_type": "Suspension System"
  },
  {
    "part_name": "Camshaft Position Sensor",
    "part_number": "CPS-044",
    "part_description": "Sensor for camshaft timing detection.",
    "price": 29.95,
    "brand_name": "Dorman",
    "part_type": "Engine"
  },
  {
    "part_name": "Axle Shaft",
    "part_number": "AS-045",
    "part_description": "Rear axle shaft for power transmission.",
    "price": 145,
    "brand_name": "Yukon",
    "part_type": "Drivetrain"
  },
  {
    "part_name": "Windshield Wiper Blade",
    "part_number": "WWB-046",
    "part_description": "All-season wiper blade for clear visibility.",
    "price": 14.5,
    "brand_name": "Rain-X",
    "part_type": "Exterior"
  },
  {
    "part_name": "Intake Manifold Gasket",
    "part_number": "IMG-047",
    "part_description": "Gasket set for intake manifold sealing.",
    "price": 18.75,
    "brand_name": "Fel-Pro",
    "part_type": "Engine"
  },
  {
    "part_name": "Parking Brake Cable",
    "part_number": "PBC-048",
    "part_description": "Durable cable for parking brake system.",
    "price": 22.99,
    "brand_name": "Dorman",
    "part_type": "Braking System"
  },
  {
    "part_name": "Crankshaft Position Sensor",
    "part_number": "CKPS-049",
    "part_description": "Sensor for crankshaft position detection.",
    "price": 32.5,
    "brand_name": "Bosch",
    "part_type": "Engine"
  },
  {
    "part_name": "Differential Cover",
    "part_number": "DC-050",
    "part_description": "Heavy-duty differential cover with gasket.",
    "price": 55,
    "brand_name": "Motive",
    "part_type": "Drivetrain"
  },
  {
    "part_name": "Fog Light",
    "part_number": "FL-051",
    "part_description": "High-intensity fog light for low-visibility conditions.",
    "price": 45.99,
    "brand_name": "Hella",
    "part_type": "Lighting"
  }
]